[
    {
        "count": 1,
        "filter": "g",
        "exptime": 20.0,
        "RA": 154.64488,
        "dec": -7.14568,
        "object": "2021afue_P2",
        "program": "DECAT",
        "expType": "object",
        "note": "None",
        "comment": "2021afue",
        "wait": "False",
        "propid": "2020B-0053"
    },
    {
        "count": 1,
        "filter": "r",
        "exptime": 20.0,
        "RA": 154.64488,
        "dec": -7.14568,
        "object": "2021afue_P2",
        "program": "DECAT",
        "expType": "object",
        "note": "None",
        "comment": "2021afue",
        "wait": "False",
        "propid": "2020B-0053"
    },
    {
        "count": 1,
        "filter": "i",
        "exptime": 20.0,
        "RA": 154.64488,
        "dec": -7.14568,
        "object": "2021afue_P2",
        "program": "DECAT",
        "expType": "object",
        "note": "None",
        "comment": "2021afue",
        "wait": "False",
        "propid": "2020B-0053"
    },
    {
        "count": 1,
        "filter": "z",
        "exptime": 20.0,
        "RA": 154.64488,
        "dec": -7.14568,
        "object": "2021afue_P2",
        "program": "DECAT",
        "expType": "object",
        "note": "None",
        "comment": "2021afue",
        "wait": "False",
        "propid": "2020B-0053"
    }
]