[
    {
        "count": 1,
        "filter": "g",
        "exptime": 5.0,
        "RA": 198.5923,
        "dec": -19.44426,
        "object": "2021fxy_P3",
        "program": "DECAT",
        "expType": "object",
        "note": "None",
        "comment": "2021fxy_P3",
        "wait": "False",
        "propid": "2020B-0053"
    },
    {
        "count": 1,
        "filter": "r",
        "exptime": 5.0,
        "RA": 198.5923,
        "dec": -19.44426,
        "object": "2021fxy_P3",
        "program": "DECAT",
        "expType": "object",
        "note": "None",
        "comment": "2021fxy_P3",
        "wait": "False",
        "propid": "2020B-0053"
    },
    {
        "count": 1,
        "filter": "i",
        "exptime": 5.0,
        "RA": 198.5923,
        "dec": -19.44426,
        "object": "2021fxy_P3",
        "program": "DECAT",
        "expType": "object",
        "note": "None",
        "comment": "2021fxy_P3",
        "wait": "False",
        "propid": "2020B-0053"
    },
    {
        "count": 1,
        "filter": "z",
        "exptime": 5.0,
        "RA": 198.5923,
        "dec": -19.44426,
        "object": "2021fxy_P3",
        "program": "DECAT",
        "expType": "object",
        "note": "None",
        "comment": "2021fxy_P3",
        "wait": "False",
        "propid": "2020B-0053"
    }
]