[
    {
        "count": 1,
        "filter": "z",
        "exptime": 90.0,
        "RA": 26.00292,
        "dec": 20.10146,
        "object": "2023tyl_P1",
        "program": "DECAT",
        "expType": "object",
        "note": "None",
        "comment": "2023tyl",
        "wait": "False",
        "propid": "2020B-0053"
    },
    {
        "count": 1,
        "filter": "i",
        "exptime": 90.0,
        "RA": 26.00292,
        "dec": 20.10146,
        "object": "2023tyl_P1",
        "program": "DECAT",
        "expType": "object",
        "note": "None",
        "comment": "2023tyl",
        "wait": "False",
        "propid": "2020B-0053"
    },
    {
        "count": 1,
        "filter": "r",
        "exptime": 90.0,
        "RA": 26.00292,
        "dec": 20.10146,
        "object": "2023tyl_P1",
        "program": "DECAT",
        "expType": "object",
        "note": "None",
        "comment": "2023tyl",
        "wait": "False",
        "propid": "2020B-0053"
    },
    {
        "count": 1,
        "filter": "g",
        "exptime": 90.0,
        "RA": 26.00292,
        "dec": 20.10146,
        "object": "2023tyl_P1",
        "program": "DECAT",
        "expType": "object",
        "note": "None",
        "comment": "2023tyl",
        "wait": "False",
        "propid": "2020B-0053"
    },
    {
        "count": 1,
        "filter": "z",
        "exptime": 30.0,
        "RA": 26.00292,
        "dec": 20.10146,
        "object": "2023tyl_P1",
        "program": "DECAT",
        "expType": "object",
        "note": "None",
        "comment": "2023tyl",
        "wait": "False",
        "propid": "2020B-0053"
    },
    {
        "count": 1,
        "filter": "i",
        "exptime": 30.0,
        "RA": 26.00292,
        "dec": 20.10146,
        "object": "2023tyl_P1",
        "program": "DECAT",
        "expType": "object",
        "note": "None",
        "comment": "2023tyl",
        "wait": "False",
        "propid": "2020B-0053"
    },
    {
        "count": 1,
        "filter": "r",
        "exptime": 30.0,
        "RA": 26.00292,
        "dec": 20.10146,
        "object": "2023tyl_P1",
        "program": "DECAT",
        "expType": "object",
        "note": "None",
        "comment": "2023tyl",
        "wait": "False",
        "propid": "2020B-0053"
    },
    {
        "count": 1,
        "filter": "g",
        "exptime": 30.0,
        "RA": 26.00292,
        "dec": 20.10146,
        "object": "2023tyl_P1",
        "program": "DECAT",
        "expType": "object",
        "note": "None",
        "comment": "2023tyl",
        "wait": "False",
        "propid": "2020B-0053"
    }
]