[
    {
        "object": "DELVE field: 6500-01-z", 
        "seqnum": 1, 
        "seqtot": 1, 
        "seqid": "DELVE scheduled: nan", 
        "expTime": 90.0000, 
        "RA": 255.1590, 
        "dec": -11.9110, 
        "filter": "z", 
        "count": 1, 
        "expType": "object", 
        "program": "delve-wide", 
        "wait": "False", 
        "propid": "2019A-0305", 
        "comment": "obztak v3.6.1+7.ge655f98: PRIORITY=-1, AIRMASS=-1.0000, SLEW=-1.0000, MOONANGLE=-1.0000, HOURANGLE=-1.0000", 
        "proposer": "Drlica-Wagner"
    }, 
    {
        "object": "DELVE field: 6501-01-z", 
        "seqnum": 1, 
        "seqtot": 1, 
        "seqid": "DELVE scheduled: nan", 
        "expTime": 90.0000, 
        "RA": 255.3920, 
        "dec": -10.1200, 
        "filter": "z", 
        "count": 1, 
        "expType": "object", 
        "program": "delve-wide", 
        "wait": "False", 
        "propid": "2019A-0305", 
        "comment": "obztak v3.6.1+7.ge655f98: PRIORITY=-1, AIRMASS=-1.0000, SLEW=-1.0000, MOONANGLE=-1.0000, HOURANGLE=-1.0000", 
        "proposer": "Drlica-Wagner"
    }, 
    {
        "object": "DELVE field: 6519-01-z", 
        "seqnum": 1, 
        "seqtot": 1, 
        "seqid": "DELVE scheduled: nan", 
        "expTime": 90.0000, 
        "RA": 256.3130, 
        "dec": -14.6000, 
        "filter": "z", 
        "count": 1, 
        "expType": "object", 
        "program": "delve-wide", 
        "wait": "False", 
        "propid": "2019A-0305", 
        "comment": "obztak v3.6.1+7.ge655f98: PRIORITY=-1, AIRMASS=-1.0000, SLEW=-1.0000, MOONANGLE=-1.0000, HOURANGLE=-1.0000", 
        "proposer": "Drlica-Wagner"
    }, 
    {
        "object": "DELVE field: 6520-01-z", 
        "seqnum": 1, 
        "seqtot": 1, 
        "seqid": "DELVE scheduled: nan", 
        "expTime": 90.0000, 
        "RA": 256.5390, 
        "dec": -12.8230, 
        "filter": "z", 
        "count": 1, 
        "expType": "object", 
        "program": "delve-wide", 
        "wait": "False", 
        "propid": "2019A-0305", 
        "comment": "obztak v3.6.1+7.ge655f98: PRIORITY=-1, AIRMASS=-1.0000, SLEW=-1.0000, MOONANGLE=-1.0000, HOURANGLE=-1.0000", 
        "proposer": "Drlica-Wagner"
    }, 
    {
        "object": "DELVE field: 6521-01-z", 
        "seqnum": 1, 
        "seqtot": 1, 
        "seqid": "DELVE scheduled: nan", 
        "expTime": 90.0000, 
        "RA": 256.7560, 
        "dec": -11.0330, 
        "filter": "z", 
        "count": 1, 
        "expType": "object", 
        "program": "delve-wide", 
        "wait": "False", 
        "propid": "2019A-0305", 
        "comment": "obztak v3.6.1+7.ge655f98: PRIORITY=-1, AIRMASS=-1.0000, SLEW=-1.0000, MOONANGLE=-1.0000, HOURANGLE=-1.0000", 
        "proposer": "Drlica-Wagner"
    }, 
    {
        "object": "DELVE field: 6541-01-z", 
        "seqnum": 1, 
        "seqtot": 1, 
        "seqid": "DELVE scheduled: nan", 
        "expTime": 90.0000, 
        "RA": 257.9380, 
        "dec": -13.7330, 
        "filter": "z", 
        "count": 1, 
        "expType": "object", 
        "program": "delve-wide", 
        "wait": "False", 
        "propid": "2019A-0305", 
        "comment": "obztak v3.6.1+7.ge655f98: PRIORITY=-1, AIRMASS=-1.0000, SLEW=-1.0000, MOONANGLE=-1.0000, HOURANGLE=-1.0000", 
        "proposer": "Drlica-Wagner"
    }, 
    {
        "object": "DELVE field: 6542-01-z", 
        "seqnum": 1, 
        "seqtot": 1, 
        "seqid": "DELVE scheduled: nan", 
        "expTime": 90.0000, 
        "RA": 258.1380, 
        "dec": -11.9460, 
        "filter": "z", 
        "count": 1, 
        "expType": "object", 
        "program": "delve-wide", 
        "wait": "False", 
        "propid": "2019A-0305", 
        "comment": "obztak v3.6.1+7.ge655f98: PRIORITY=-1, AIRMASS=-1.0000, SLEW=-1.0000, MOONANGLE=-1.0000, HOURANGLE=-1.0000", 
        "proposer": "Drlica-Wagner"
    }, 
    {
        "object": "DELVE field: 6543-01-z", 
        "seqnum": 1, 
        "seqtot": 1, 
        "seqid": "DELVE scheduled: nan", 
        "expTime": 90.0000, 
        "RA": 258.3270, 
        "dec": -10.1450, 
        "filter": "z", 
        "count": 1, 
        "expType": "object", 
        "program": "delve-wide", 
        "wait": "False", 
        "propid": "2019A-0305", 
        "comment": "obztak v3.6.1+7.ge655f98: PRIORITY=-1, AIRMASS=-1.0000, SLEW=-1.0000, MOONANGLE=-1.0000, HOURANGLE=-1.0000", 
        "proposer": "Drlica-Wagner"
    }, 
    {
        "object": "DELVE field: 6563-01-z", 
        "seqnum": 1, 
        "seqtot": 1, 
        "seqid": "DELVE scheduled: nan", 
        "expTime": 90.0000, 
        "RA": 259.3570, 
        "dec": -14.6410, 
        "filter": "z", 
        "count": 1, 
        "expType": "object", 
        "program": "delve-wide", 
        "wait": "False", 
        "propid": "2019A-0305", 
        "comment": "obztak v3.6.1+7.ge655f98: PRIORITY=-1, AIRMASS=-1.0000, SLEW=-1.0000, MOONANGLE=-1.0000, HOURANGLE=-1.0000", 
        "proposer": "Drlica-Wagner"
    }, 
    {
        "object": "DELVE field: 6564-01-z", 
        "seqnum": 1, 
        "seqtot": 1, 
        "seqid": "DELVE scheduled: nan", 
        "expTime": 90.0000, 
        "RA": 259.5370, 
        "dec": -12.8560, 
        "filter": "z", 
        "count": 1, 
        "expType": "object", 
        "program": "delve-wide", 
        "wait": "False", 
        "propid": "2019A-0305", 
        "comment": "obztak v3.6.1+7.ge655f98: PRIORITY=-1, AIRMASS=-1.0000, SLEW=-1.0000, MOONANGLE=-1.0000, HOURANGLE=-1.0000", 
        "proposer": "Drlica-Wagner"
    }, 
    {
        "object": "DELVE field: 6565-01-z", 
        "seqnum": 1, 
        "seqtot": 1, 
        "seqid": "DELVE scheduled: nan", 
        "expTime": 90.0000, 
        "RA": 259.7100, 
        "dec": -11.0590, 
        "filter": "z", 
        "count": 1, 
        "expType": "object", 
        "program": "delve-wide", 
        "wait": "False", 
        "propid": "2019A-0305", 
        "comment": "obztak v3.6.1+7.ge655f98: PRIORITY=-1, AIRMASS=-1.0000, SLEW=-1.0000, MOONANGLE=-1.0000, HOURANGLE=-1.0000", 
        "proposer": "Drlica-Wagner"
    }, 
    {
        "object": "DELVE field: 6583-01-z", 
        "seqnum": 1, 
        "seqtot": 1, 
        "seqid": "DELVE scheduled: nan", 
        "expTime": 90.0000, 
        "RA": 260.9580, 
        "dec": -13.7660, 
        "filter": "z", 
        "count": 1, 
        "expType": "object", 
        "program": "delve-wide", 
        "wait": "False", 
        "propid": "2019A-0305", 
        "comment": "obztak v3.6.1+7.ge655f98: PRIORITY=-1, AIRMASS=-1.0000, SLEW=-1.0000, MOONANGLE=-1.0000, HOURANGLE=-1.0000", 
        "proposer": "Drlica-Wagner"
    }, 
    {
        "object": "DELVE field: 6584-01-z", 
        "seqnum": 1, 
        "seqtot": 1, 
        "seqid": "DELVE scheduled: nan", 
        "expTime": 90.0000, 
        "RA": 261.1110, 
        "dec": -11.9710, 
        "filter": "z", 
        "count": 1, 
        "expType": "object", 
        "program": "delve-wide", 
        "wait": "False", 
        "propid": "2019A-0305", 
        "comment": "obztak v3.6.1+7.ge655f98: PRIORITY=-1, AIRMASS=-1.0000, SLEW=-1.0000, MOONANGLE=-1.0000, HOURANGLE=-1.0000", 
        "proposer": "Drlica-Wagner"
    }, 
    {
        "object": "DELVE field: 6585-01-z", 
        "seqnum": 1, 
        "seqtot": 1, 
        "seqid": "DELVE scheduled: nan", 
        "expTime": 90.0000, 
        "RA": 261.2510, 
        "dec": -10.1610, 
        "filter": "z", 
        "count": 1, 
        "expType": "object", 
        "program": "delve-wide", 
        "wait": "False", 
        "propid": "2019A-0305", 
        "comment": "obztak v3.6.1+7.ge655f98: PRIORITY=-1, AIRMASS=-1.0000, SLEW=-1.0000, MOONANGLE=-1.0000, HOURANGLE=-1.0000", 
        "proposer": "Drlica-Wagner"
    }, 
    {
        "object": "DELVE field: 6599-01-z", 
        "seqnum": 1, 
        "seqtot": 1, 
        "seqid": "DELVE scheduled: nan", 
        "expTime": 90.0000, 
        "RA": 262.4000, 
        "dec": -14.6730, 
        "filter": "z", 
        "count": 1, 
        "expType": "object", 
        "program": "delve-wide", 
        "wait": "False", 
        "propid": "2019A-0305", 
        "comment": "obztak v3.6.1+7.ge655f98: PRIORITY=-1, AIRMASS=-1.0000, SLEW=-1.0000, MOONANGLE=-1.0000, HOURANGLE=-1.0000", 
        "proposer": "Drlica-Wagner"
    }, 
    {
        "object": "DELVE field: 6600-01-z", 
        "seqnum": 1, 
        "seqtot": 1, 
        "seqid": "DELVE scheduled: nan", 
        "expTime": 90.0000, 
        "RA": 262.5320, 
        "dec": -12.8820, 
        "filter": "z", 
        "count": 1, 
        "expType": "object", 
        "program": "delve-wide", 
        "wait": "False", 
        "propid": "2019A-0305", 
        "comment": "obztak v3.6.1+7.ge655f98: PRIORITY=-1, AIRMASS=-1.0000, SLEW=-1.0000, MOONANGLE=-1.0000, HOURANGLE=-1.0000", 
        "proposer": "Drlica-Wagner"
    }, 
    {
        "object": "DELVE field: 6601-01-z", 
        "seqnum": 1, 
        "seqtot": 1, 
        "seqid": "DELVE scheduled: nan", 
        "expTime": 90.0000, 
        "RA": 262.6550, 
        "dec": -11.0750, 
        "filter": "z", 
        "count": 1, 
        "expType": "object", 
        "program": "delve-wide", 
        "wait": "False", 
        "propid": "2019A-0305", 
        "comment": "obztak v3.6.1+7.ge655f98: PRIORITY=-1, AIRMASS=-1.0000, SLEW=-1.0000, MOONANGLE=-1.0000, HOURANGLE=-1.0000", 
        "proposer": "Drlica-Wagner"
    }, 
    {
        "object": "DELVE field: 6614-01-z", 
        "seqnum": 1, 
        "seqtot": 1, 
        "seqid": "DELVE scheduled: nan", 
        "expTime": 90.0000, 
        "RA": 264.0770, 
        "dec": -11.9880, 
        "filter": "z", 
        "count": 1, 
        "expType": "object", 
        "program": "delve-wide", 
        "wait": "False", 
        "propid": "2019A-0305", 
        "comment": "obztak v3.6.1+7.ge655f98: PRIORITY=-1, AIRMASS=-1.0000, SLEW=-1.0000, MOONANGLE=-1.0000, HOURANGLE=-1.0000", 
        "proposer": "Drlica-Wagner"
    }, 
    {
        "object": "DELVE field: 6603-01-z", 
        "seqnum": 1, 
        "seqtot": 1, 
        "seqid": "DELVE scheduled: nan", 
        "expTime": 90.0000, 
        "RA": 264.1700, 
        "dec": -10.1720, 
        "filter": "z", 
        "count": 1, 
        "expType": "object", 
        "program": "delve-wide", 
        "wait": "False", 
        "propid": "2019A-0305", 
        "comment": "obztak v3.6.1+7.ge655f98: PRIORITY=-1, AIRMASS=-1.0000, SLEW=-1.0000, MOONANGLE=-1.0000, HOURANGLE=-1.0000", 
        "proposer": "Drlica-Wagner"
    }
]