[
    {
        "object": "DELVE field: 1490-01-z", 
        "seqnum": 1, 
        "seqtot": 1, 
        "seqid": "DELVE scheduled: nan", 
        "expTime": 90.0000, 
        "RA": 295.1220, 
        "dec": -16.6210, 
        "filter": "z", 
        "count": 1, 
        "expType": "object", 
        "program": "delve-wide", 
        "wait": "False", 
        "propid": "2019A-0305", 
        "comment": "obztak v3.6.1+7.ge655f98: PRIORITY=1, AIRMASS=-1.0000, SLEW=-1.0000, MOONANGLE=-1.0000, HOURANGLE=-1.0000", 
        "proposer": "Drlica-Wagner"
    }, 
    {
        "object": "DELVE field: 594-01-z", 
        "seqnum": 1, 
        "seqtot": 1, 
        "seqid": "DELVE scheduled: nan", 
        "expTime": 90.0000, 
        "RA": 295.5700, 
        "dec": -18.2400, 
        "filter": "z", 
        "count": 1, 
        "expType": "object", 
        "program": "delve-wide", 
        "wait": "False", 
        "propid": "2019A-0305", 
        "comment": "obztak v3.6.1+7.ge655f98: PRIORITY=1, AIRMASS=-1.0000, SLEW=-1.0000, MOONANGLE=-1.0000, HOURANGLE=-1.0000", 
        "proposer": "Drlica-Wagner"
    }, 
    {
        "object": "DELVE field: 606-01-z", 
        "seqnum": 1, 
        "seqtot": 1, 
        "seqid": "DELVE scheduled: nan", 
        "expTime": 90.0000, 
        "RA": 296.0310, 
        "dec": -19.8470, 
        "filter": "z", 
        "count": 1, 
        "expType": "object", 
        "program": "delve-wide", 
        "wait": "False", 
        "propid": "2019A-0305", 
        "comment": "obztak v3.6.1+7.ge655f98: PRIORITY=1, AIRMASS=-1.0000, SLEW=-1.0000, MOONANGLE=-1.0000, HOURANGLE=-1.0000", 
        "proposer": "Drlica-Wagner"
    }, 
    {
        "object": "DELVE field: 585-01-z", 
        "seqnum": 1, 
        "seqtot": 1, 
        "seqid": "DELVE scheduled: nan", 
        "expTime": 90.0000, 
        "RA": 296.5040, 
        "dec": -15.6230, 
        "filter": "z", 
        "count": 1, 
        "expType": "object", 
        "program": "delve-wide", 
        "wait": "False", 
        "propid": "2019A-0305", 
        "comment": "obztak v3.6.1+7.ge655f98: PRIORITY=-1, AIRMASS=-1.0000, SLEW=-1.0000, MOONANGLE=-1.0000, HOURANGLE=-1.0000", 
        "proposer": "Drlica-Wagner"
    }, 
    {
        "object": "DELVE field: 595-01-z", 
        "seqnum": 1, 
        "seqtot": 1, 
        "seqid": "DELVE scheduled: nan", 
        "expTime": 90.0000, 
        "RA": 296.9680, 
        "dec": -17.2240, 
        "filter": "z", 
        "count": 1, 
        "expType": "object", 
        "program": "delve-wide", 
        "wait": "False", 
        "propid": "2019A-0305", 
        "comment": "obztak v3.6.1+7.ge655f98: PRIORITY=1, AIRMASS=-1.0000, SLEW=-1.0000, MOONANGLE=-1.0000, HOURANGLE=-1.0000", 
        "proposer": "Drlica-Wagner"
    }, 
    {
        "object": "DELVE field: 607-01-z", 
        "seqnum": 1, 
        "seqtot": 1, 
        "seqid": "DELVE scheduled: nan", 
        "expTime": 90.0000, 
        "RA": 297.4420, 
        "dec": -18.8150, 
        "filter": "z", 
        "count": 1, 
        "expType": "object", 
        "program": "delve-wide", 
        "wait": "False", 
        "propid": "2019A-0305", 
        "comment": "obztak v3.6.1+7.ge655f98: PRIORITY=1, AIRMASS=-1.0000, SLEW=-1.0000, MOONANGLE=-1.0000, HOURANGLE=-1.0000", 
        "proposer": "Drlica-Wagner"
    }, 
    {
        "object": "DELVE field: 596-01-z", 
        "seqnum": 1, 
        "seqtot": 1, 
        "seqid": "DELVE scheduled: nan", 
        "expTime": 90.0000, 
        "RA": 298.3550, 
        "dec": -16.1840, 
        "filter": "z", 
        "count": 1, 
        "expType": "object", 
        "program": "delve-wide", 
        "wait": "False", 
        "propid": "2019A-0305", 
        "comment": "obztak v3.6.1+7.ge655f98: PRIORITY=1, AIRMASS=-1.0000, SLEW=-1.0000, MOONANGLE=-1.0000, HOURANGLE=-1.0000", 
        "proposer": "Drlica-Wagner"
    }, 
    {
        "object": "DELVE field: 608-01-z", 
        "seqnum": 1, 
        "seqtot": 1, 
        "seqid": "DELVE scheduled: nan", 
        "expTime": 90.0000, 
        "RA": 298.8400, 
        "dec": -17.7560, 
        "filter": "z", 
        "count": 1, 
        "expType": "object", 
        "program": "delve-wide", 
        "wait": "False", 
        "propid": "2019A-0305", 
        "comment": "obztak v3.6.1+7.ge655f98: PRIORITY=1, AIRMASS=-1.0000, SLEW=-1.0000, MOONANGLE=-1.0000, HOURANGLE=-1.0000", 
        "proposer": "Drlica-Wagner"
    }, 
    {
        "object": "DELVE field: 621-01-z", 
        "seqnum": 1, 
        "seqtot": 1, 
        "seqid": "DELVE scheduled: nan", 
        "expTime": 90.0000, 
        "RA": 299.3350, 
        "dec": -19.3240, 
        "filter": "z", 
        "count": 1, 
        "expType": "object", 
        "program": "delve-wide", 
        "wait": "False", 
        "propid": "2019A-0305", 
        "comment": "obztak v3.6.1+7.ge655f98: PRIORITY=-1, AIRMASS=-1.0000, SLEW=-1.0000, MOONANGLE=-1.0000, HOURANGLE=-1.0000", 
        "proposer": "Drlica-Wagner"
    }, 
    {
        "object": "DELVE field: 597-01-z", 
        "seqnum": 1, 
        "seqtot": 1, 
        "seqid": "DELVE scheduled: nan", 
        "expTime": 90.0000, 
        "RA": 299.7330, 
        "dec": -15.1140, 
        "filter": "z", 
        "count": 1, 
        "expType": "object", 
        "program": "delve-wide", 
        "wait": "False", 
        "propid": "2019A-0305", 
        "comment": "obztak v3.6.1+7.ge655f98: PRIORITY=-1, AIRMASS=-1.0000, SLEW=-1.0000, MOONANGLE=-1.0000, HOURANGLE=-1.0000", 
        "proposer": "Drlica-Wagner"
    }, 
    {
        "object": "DELVE field: 609-01-z", 
        "seqnum": 1, 
        "seqtot": 1, 
        "seqid": "DELVE scheduled: nan", 
        "expTime": 90.0000, 
        "RA": 300.2280, 
        "dec": -16.6680, 
        "filter": "z", 
        "count": 1, 
        "expType": "object", 
        "program": "delve-wide", 
        "wait": "False", 
        "propid": "2019A-0305", 
        "comment": "obztak v3.6.1+7.ge655f98: PRIORITY=-1, AIRMASS=-1.0000, SLEW=-1.0000, MOONANGLE=-1.0000, HOURANGLE=-1.0000", 
        "proposer": "Drlica-Wagner"
    }, 
    {
        "object": "DELVE field: 622-01-z", 
        "seqnum": 1, 
        "seqtot": 1, 
        "seqid": "DELVE scheduled: nan", 
        "expTime": 90.0000, 
        "RA": 300.7310, 
        "dec": -18.2200, 
        "filter": "z", 
        "count": 1, 
        "expType": "object", 
        "program": "delve-wide", 
        "wait": "False", 
        "propid": "2019A-0305", 
        "comment": "obztak v3.6.1+7.ge655f98: PRIORITY=-1, AIRMASS=-1.0000, SLEW=-1.0000, MOONANGLE=-1.0000, HOURANGLE=-1.0000", 
        "proposer": "Drlica-Wagner"
    }, 
    {
        "object": "DELVE field: 637-01-z", 
        "seqnum": 1, 
        "seqtot": 1, 
        "seqid": "DELVE scheduled: nan", 
        "expTime": 90.0000, 
        "RA": 301.2430, 
        "dec": -19.7720, 
        "filter": "z", 
        "count": 1, 
        "expType": "object", 
        "program": "delve-wide", 
        "wait": "False", 
        "propid": "2019A-0305", 
        "comment": "obztak v3.6.1+7.ge655f98: PRIORITY=-1, AIRMASS=-1.0000, SLEW=-1.0000, MOONANGLE=-1.0000, HOURANGLE=-1.0000", 
        "proposer": "Drlica-Wagner"
    }, 
    {
        "object": "DELVE field: 610-01-z", 
        "seqnum": 1, 
        "seqtot": 1, 
        "seqid": "DELVE scheduled: nan", 
        "expTime": 90.0000, 
        "RA": 301.6040, 
        "dec": -15.5440, 
        "filter": "z", 
        "count": 1, 
        "expType": "object", 
        "program": "delve-wide", 
        "wait": "False", 
        "propid": "2019A-0305", 
        "comment": "obztak v3.6.1+7.ge655f98: PRIORITY=-1, AIRMASS=-1.0000, SLEW=-1.0000, MOONANGLE=-1.0000, HOURANGLE=-1.0000", 
        "proposer": "Drlica-Wagner"
    }, 
    {
        "object": "DELVE field: 623-01-z", 
        "seqnum": 1, 
        "seqtot": 1, 
        "seqid": "DELVE scheduled: nan", 
        "expTime": 90.0000, 
        "RA": 302.1130, 
        "dec": -17.0810, 
        "filter": "z", 
        "count": 1, 
        "expType": "object", 
        "program": "delve-wide", 
        "wait": "False", 
        "propid": "2019A-0305", 
        "comment": "obztak v3.6.1+7.ge655f98: PRIORITY=-1, AIRMASS=-1.0000, SLEW=-1.0000, MOONANGLE=-1.0000, HOURANGLE=-1.0000", 
        "proposer": "Drlica-Wagner"
    }, 
    {
        "object": "DELVE field: 638-01-z", 
        "seqnum": 1, 
        "seqtot": 1, 
        "seqid": "DELVE scheduled: nan", 
        "expTime": 90.0000, 
        "RA": 302.6310, 
        "dec": -18.6190, 
        "filter": "z", 
        "count": 1, 
        "expType": "object", 
        "program": "delve-wide", 
        "wait": "False", 
        "propid": "2019A-0305", 
        "comment": "obztak v3.6.1+7.ge655f98: PRIORITY=-1, AIRMASS=-1.0000, SLEW=-1.0000, MOONANGLE=-1.0000, HOURANGLE=-1.0000", 
        "proposer": "Drlica-Wagner"
    }, 
    {
        "object": "DELVE field: 624-01-z", 
        "seqnum": 1, 
        "seqtot": 1, 
        "seqid": "DELVE scheduled: nan", 
        "expTime": 90.0000, 
        "RA": 303.4810, 
        "dec": -15.9030, 
        "filter": "z", 
        "count": 1, 
        "expType": "object", 
        "program": "delve-wide", 
        "wait": "False", 
        "propid": "2019A-0305", 
        "comment": "obztak v3.6.1+7.ge655f98: PRIORITY=-1, AIRMASS=-1.0000, SLEW=-1.0000, MOONANGLE=-1.0000, HOURANGLE=-1.0000", 
        "proposer": "Drlica-Wagner"
    }, 
    {
        "object": "DELVE field: 639-01-z", 
        "seqnum": 1, 
        "seqtot": 1, 
        "seqid": "DELVE scheduled: nan", 
        "expTime": 90.0000, 
        "RA": 304.0020, 
        "dec": -17.4300, 
        "filter": "z", 
        "count": 1, 
        "expType": "object", 
        "program": "delve-wide", 
        "wait": "False", 
        "propid": "2019A-0305", 
        "comment": "obztak v3.6.1+7.ge655f98: PRIORITY=-1, AIRMASS=-1.0000, SLEW=-1.0000, MOONANGLE=-1.0000, HOURANGLE=-1.0000", 
        "proposer": "Drlica-Wagner"
    }, 
    {
        "object": "DELVE field: 655-01-z", 
        "seqnum": 1, 
        "seqtot": 1, 
        "seqid": "DELVE scheduled: nan", 
        "expTime": 90.0000, 
        "RA": 304.5330, 
        "dec": -18.9620, 
        "filter": "z", 
        "count": 1, 
        "expType": "object", 
        "program": "delve-wide", 
        "wait": "False", 
        "propid": "2019A-0305", 
        "comment": "obztak v3.6.1+7.ge655f98: PRIORITY=-1, AIRMASS=-1.0000, SLEW=-1.0000, MOONANGLE=-1.0000, HOURANGLE=-1.0000", 
        "proposer": "Drlica-Wagner"
    }, 
    {
        "object": "DELVE field: 640-01-z", 
        "seqnum": 1, 
        "seqtot": 1, 
        "seqid": "DELVE scheduled: nan", 
        "expTime": 90.0000, 
        "RA": 305.3550, 
        "dec": -16.2010, 
        "filter": "z", 
        "count": 1, 
        "expType": "object", 
        "program": "delve-wide", 
        "wait": "False", 
        "propid": "2019A-0305", 
        "comment": "obztak v3.6.1+7.ge655f98: PRIORITY=-1, AIRMASS=-1.0000, SLEW=-1.0000, MOONANGLE=-1.0000, HOURANGLE=-1.0000", 
        "proposer": "Drlica-Wagner"
    }, 
    {
        "object": "DELVE field: 656-01-z", 
        "seqnum": 1, 
        "seqtot": 1, 
        "seqid": "DELVE scheduled: nan", 
        "expTime": 90.0000, 
        "RA": 305.8880, 
        "dec": -17.7240, 
        "filter": "z", 
        "count": 1, 
        "expType": "object", 
        "program": "delve-wide", 
        "wait": "False", 
        "propid": "2019A-0305", 
        "comment": "obztak v3.6.1+7.ge655f98: PRIORITY=-1, AIRMASS=-1.0000, SLEW=-1.0000, MOONANGLE=-1.0000, HOURANGLE=-1.0000", 
        "proposer": "Drlica-Wagner"
    }, 
    {
        "object": "DELVE field: 673-01-z", 
        "seqnum": 1, 
        "seqtot": 1, 
        "seqid": "DELVE scheduled: nan", 
        "expTime": 90.0000, 
        "RA": 306.4330, 
        "dec": -19.2530, 
        "filter": "z", 
        "count": 1, 
        "expType": "object", 
        "program": "delve-wide", 
        "wait": "False", 
        "propid": "2019A-0305", 
        "comment": "obztak v3.6.1+7.ge655f98: PRIORITY=-1, AIRMASS=-1.0000, SLEW=-1.0000, MOONANGLE=-1.0000, HOURANGLE=-1.0000", 
        "proposer": "Drlica-Wagner"
    }, 
    {
        "object": "DELVE field: 657-01-z", 
        "seqnum": 1, 
        "seqtot": 1, 
        "seqid": "DELVE scheduled: nan", 
        "expTime": 90.0000, 
        "RA": 307.2240, 
        "dec": -16.4550, 
        "filter": "z", 
        "count": 1, 
        "expType": "object", 
        "program": "delve-wide", 
        "wait": "False", 
        "propid": "2019A-0305", 
        "comment": "obztak v3.6.1+7.ge655f98: PRIORITY=-1, AIRMASS=-1.0000, SLEW=-1.0000, MOONANGLE=-1.0000, HOURANGLE=-1.0000", 
        "proposer": "Drlica-Wagner"
    }, 
    {
        "object": "DELVE field: 674-01-z", 
        "seqnum": 1, 
        "seqtot": 1, 
        "seqid": "DELVE scheduled: nan", 
        "expTime": 90.0000, 
        "RA": 307.7700, 
        "dec": -17.9780, 
        "filter": "z", 
        "count": 1, 
        "expType": "object", 
        "program": "delve-wide", 
        "wait": "False", 
        "propid": "2019A-0305", 
        "comment": "obztak v3.6.1+7.ge655f98: PRIORITY=-1, AIRMASS=-1.0000, SLEW=-1.0000, MOONANGLE=-1.0000, HOURANGLE=-1.0000", 
        "proposer": "Drlica-Wagner"
    }, 
    {
        "object": "DELVE field: 692-01-z", 
        "seqnum": 1, 
        "seqtot": 1, 
        "seqid": "DELVE scheduled: nan", 
        "expTime": 90.0000, 
        "RA": 308.3280, 
        "dec": -19.5080, 
        "filter": "z", 
        "count": 1, 
        "expType": "object", 
        "program": "delve-wide", 
        "wait": "False", 
        "propid": "2019A-0305", 
        "comment": "obztak v3.6.1+7.ge655f98: PRIORITY=-1, AIRMASS=-1.0000, SLEW=-1.0000, MOONANGLE=-1.0000, HOURANGLE=-1.0000", 
        "proposer": "Drlica-Wagner"
    }, 
    {
        "object": "DELVE field: 658-01-z", 
        "seqnum": 1, 
        "seqtot": 1, 
        "seqid": "DELVE scheduled: nan", 
        "expTime": 90.0000, 
        "RA": 308.5420, 
        "dec": -15.1610, 
        "filter": "z", 
        "count": 1, 
        "expType": "object", 
        "program": "delve-wide", 
        "wait": "False", 
        "propid": "2019A-0305", 
        "comment": "obztak v3.6.1+7.ge655f98: PRIORITY=-1, AIRMASS=-1.0000, SLEW=-1.0000, MOONANGLE=-1.0000, HOURANGLE=-1.0000", 
        "proposer": "Drlica-Wagner"
    }, 
    {
        "object": "DELVE field: 675-01-z", 
        "seqnum": 1, 
        "seqtot": 1, 
        "seqid": "DELVE scheduled: nan", 
        "expTime": 90.0000, 
        "RA": 309.0880, 
        "dec": -16.6790, 
        "filter": "z", 
        "count": 1, 
        "expType": "object", 
        "program": "delve-wide", 
        "wait": "False", 
        "propid": "2019A-0305", 
        "comment": "obztak v3.6.1+7.ge655f98: PRIORITY=-1, AIRMASS=-1.0000, SLEW=-1.0000, MOONANGLE=-1.0000, HOURANGLE=-1.0000", 
        "proposer": "Drlica-Wagner"
    }, 
    {
        "object": "DELVE field: 693-01-z", 
        "seqnum": 1, 
        "seqtot": 1, 
        "seqid": "DELVE scheduled: nan", 
        "expTime": 90.0000, 
        "RA": 309.6460, 
        "dec": -18.2030, 
        "filter": "z", 
        "count": 1, 
        "expType": "object", 
        "program": "delve-wide", 
        "wait": "False", 
        "propid": "2019A-0305", 
        "comment": "obztak v3.6.1+7.ge655f98: PRIORITY=-1, AIRMASS=-1.0000, SLEW=-1.0000, MOONANGLE=-1.0000, HOURANGLE=-1.0000", 
        "proposer": "Drlica-Wagner"
    }
]