[
{
  "count": 1,
  "expType": "object",
  "object": "twilight1",
  "filter": "r",
  "RA": "14:16:00.0",
  "dec": "-21:00:00.0",
  "expTime": 35,
  "program": "A Twilight Survey For Asteroids Interior to Earths Orbit", 
  "proposer": "Sheppard",
  "propid": "2021B-0909",
  "earlyTime": "2022-12-16 08:21:00Z",
  "lateTime": "2022-12-16 08:38:00Z"
 },
 {
  "count": 1,
  "expType": "object",
  "object": "twilight2",
  "filter": "r",
  "RA": "14:20:00.0",
  "dec": "-22:30:00.0",
  "expTime": 35,
  "program": "A Twilight Survey For Asteroids Interior to Earths Orbit", 
  "proposer": "Sheppard",
  "propid": "2021B-0909",
  "earlyTime": "2022-12-16 08:21:00Z",
  "lateTime": "2022-12-16 08:38:00Z"
},
{
  "count": 1,
  "expType": "object",
  "object": "twilight3",
  "filter": "r",
  "RA": "14:24:00.0",
  "dec": "-24:00:00.0",
  "expTime": 30,
  "program": "A Twilight Survey For Asteroids Interior to Earths Orbit", 
  "proposer": "Sheppard",
  "propid": "2021B-0909",
  "earlyTime": "2022-12-16 08:21:00Z",
  "lateTime": "2022-12-16 08:38:00Z"
},
{
  "count": 1,
  "expType": "object",
  "object": "twilight1",
  "filter": "r",
  "RA": "14:16:00.0",
  "dec": "-21:00:00.0",
  "expTime": 35,
  "program": "A Twilight Survey For Asteroids Interior to Earths Orbit", 
  "proposer": "Sheppard",
  "propid": "2021B-0909",
  "earlyTime": "2022-12-16 08:21:00Z",
  "lateTime": "2022-12-16 08:38:00Z"
},
{
  "count": 1,
  "expType": "object",
  "object": "twilight2",
  "filter": "r",
  "RA": "14:20:00.0",
  "dec": "-22:30:00.0",
  "expTime": 35,
  "program": "A Twilight Survey For Asteroids Interior to Earths Orbit", 
  "proposer": "Sheppard",
  "propid": "2021B-0909",
  "earlyTime": "2022-12-16 08:21:00Z",
  "lateTime": "2022-12-16 08:38:00Z"
},
{
  "count": 1,
  "expType": "object",
  "object": "twilight3",
  "filter": "r",
  "RA": "14:24:00.0",
  "dec": "-24:00:00.0",
  "expTime": 30,
  "program": "A Twilight Survey For Asteroids Interior to Earths Orbit", 
  "proposer": "Sheppard",
  "propid": "2021B-0909",
  "earlyTime": "2022-12-16 08:21:00Z",
  "lateTime": "2022-12-16 08:38:00Z"
}
]
