[
{
"count": 1,
"expType": "object",
"object": "2024exw",
"filter": "g",
"expTime": 10,
"RA": "183.3618",
"dec": "14.8649",
"propid": "2024B-763968"
},
{
"count": 1,
"expType": "object",
"object": "2024exw",
"filter": "r",
"expTime": 10,
"RA": "183.3618",
"dec": "14.8649",
"propid": "2024B-763968"
},
{
"count": 1,
"expType": "object",
"object": "2024exw",
"filter": "i",
"expTime": 10,
"RA": "183.3618",
"dec": "14.8649",
"propid": "2024B-763968"
},
{
"count": 1,
"expType": "object",
"object": "2024exw",
"filter": "z",
"expTime": 10,
"RA": "183.3618",
"dec": "14.8649",
"propid": "2024B-763968"
}
]
